sdr/__init__.py
sdr/_conversion.py
sdr/_data.py
sdr/_farrow.py
sdr/_helper.py
sdr/_nco.py
sdr/_probability.py
sdr/_signal.py
sdr/_version.py
sdr/_coding/__init__.py
sdr/_coding/_interleaver.py
sdr/_coding/_scrambler.py
sdr/_detection/__init__.py
sdr/_detection/_approximation.py
sdr/_detection/_coherent_integration.py
sdr/_detection/_correlator.py
sdr/_detection/_energy.py
sdr/_detection/_non_coherent_integration.py
sdr/_detection/_theory.py
sdr/_estimation/__init__.py
sdr/_estimation/_frequency.py
sdr/_estimation/_snr.py
sdr/_estimation/_time.py
sdr/_filter/__init__.py
sdr/_filter/_applications.py
sdr/_filter/_common.py
sdr/_filter/_delay.py
sdr/_filter/_design_fir.py
sdr/_filter/_design_multirate.py
sdr/_filter/_fir.py
sdr/_filter/_iir.py
sdr/_filter/_polyphase.py
sdr/_link_budget/__init__.py
sdr/_link_budget/_antenna.py
sdr/_link_budget/_capacity.py
sdr/_link_budget/_path_loss.py
sdr/_measurement/__init__.py
sdr/_measurement/_distance.py
sdr/_measurement/_energy.py
sdr/_measurement/_errors.py
sdr/_measurement/_modulation.py
sdr/_measurement/_power.py
sdr/_measurement/_voltage.py
sdr/_modulation/__init__.py
sdr/_modulation/_cpm.py
sdr/_modulation/_linear.py
sdr/_modulation/_msk.py
sdr/_modulation/_psk.py
sdr/_modulation/_pulse_shapes.py
sdr/_modulation/_symbol_encoding.py
sdr/_sequence/__init__.py
sdr/_sequence/_conversion.py
sdr/_sequence/_correlation.py
sdr/_sequence/_lfsr.py
sdr/_sequence/_maximum.py
sdr/_sequence/_symbol_mapping.py
sdr/_simulation/__init__.py
sdr/_simulation/_channel_model.py
sdr/_simulation/_impairment.py
sdr/_synchronization/__init__.py
sdr/_synchronization/_agc.py
sdr/_synchronization/_loop_filter.py
sdr/_synchronization/_phase_error.py
sdr/_synchronization/_pll.py
sdr/plot/__init__.py
sdr/plot/_detection.py
sdr/plot/_filter.py
sdr/plot/_freq_domain.py
sdr/plot/_helper.py
sdr/plot/_modulation.py
sdr/plot/_rc_params.py
sdr/plot/_spectral_estimation.py
sdr/plot/_time_domain.py
sdr/plot/_utility.py
sdr-0.0.29.dist-info/LICENSE
sdr-0.0.29.dist-info/METADATA
sdr-0.0.29.dist-info/WHEEL
sdr-0.0.29.dist-info/top_level.txt
sdr-0.0.29.dist-info/RECORD
