Metadata-Version: 2.1
Name: sdr
Version: 0.0.29
Summary: A Python package for software-defined radio
Author-email: Matt Hostetter <matthostetter@gmail.com>
License: MIT
Project-URL: Homepage, https://github.com/mhostetter/sdr
Project-URL: Source, https://github.com/mhostetter/sdr
Project-URL: Issues, https://github.com/mhostetter/sdr/issues
Project-URL: Documentation, https://mhostetter.github.io/sdr/latest/
Project-URL: Discuss, https://github.com/mhostetter/sdr/discussions
Project-URL: Twitter, https://twitter.com/sdr_py
Keywords: software-defined radio,sdr,digital communications,wireless communications,digital signal processing,dsp,modulation,demodulation,modem,forward error correction,numpy
Classifier: Development Status :: 3 - Alpha
Classifier: Intended Audience :: Developers
Classifier: Intended Audience :: Education
Classifier: Intended Audience :: Science/Research
Classifier: Intended Audience :: Telecommunications Industry
Classifier: License :: OSI Approved :: MIT License
Classifier: Operating System :: MacOS :: MacOS X
Classifier: Operating System :: Microsoft :: Windows
Classifier: Operating System :: POSIX :: Linux
Classifier: Programming Language :: Python :: 3
Classifier: Programming Language :: Python :: 3 :: Only
Classifier: Programming Language :: Python :: 3.8
Classifier: Programming Language :: Python :: 3.9
Classifier: Programming Language :: Python :: 3.10
Classifier: Programming Language :: Python :: 3.11
Classifier: Programming Language :: Python :: 3.12
Classifier: Programming Language :: Python :: 3.13
Classifier: Topic :: Scientific/Engineering :: Mathematics
Classifier: Topic :: Security :: Cryptography
Classifier: Topic :: Software Development :: Libraries :: Python Modules
Classifier: Typing :: Typed
Requires-Python: >=3.8
License-File: LICENSE
Requires-Dist: numpy
Requires-Dist: numba
Requires-Dist: scipy
Requires-Dist: matplotlib
Requires-Dist: galois==0.4.4
Requires-Dist: typing-extensions>=4.0.0
